breeze/__init__.py
breeze/cli.py
breeze/commands/__init__.py
breeze/commands/add.py
breeze/commands/build.py
breeze/commands/config.py
breeze/models/__init__.py
breeze/models/model.py
breeze/models/source.py
breeze/models/tests.py
breeze/templates/default_model_template.sql
breeze/templates/default_model_template.yml
breeze/templates/default_semantic_model_template.yml
breeze/templates/default_source_template.yml
breeze/templates/default_test_template.sql
breeze/utils/__init__.py
breeze/utils/ai_utils.py
breeze/utils/config_utils.py
breeze/utils/db_utils.py
breeze/utils/dbt_utils.py
breeze/utils/manifest_utils.py
breeze/utils/template_utils.py
breeze/utils/utils.py
breeze/utils/yaml_utils.py
breeze_dbt_cli-0.5.1.dist-info/METADATA
breeze_dbt_cli-0.5.1.dist-info/WHEEL
breeze_dbt_cli-0.5.1.dist-info/entry_points.txt
breeze_dbt_cli-0.5.1.dist-info/top_level.txt
breeze_dbt_cli-0.5.1.dist-info/RECORD
