Metadata-Version: 2.4
Name: breeze-dbt-cli
Version: 0.5.1
Summary: A CLI tool to streamline dbt project development.
Home-page: https://github.com/alecab94/breeze-dbt-cli
Author: Alejandro Cabrera
Author-email: alecab1994@gmail.com
Classifier: Programming Language :: Python :: 3
Classifier: License :: OSI Approved :: MIT License
Classifier: Operating System :: OS Independent
Requires-Python: >=3.6
Requires-Dist: typer[all]
Requires-Dist: pyyaml
Requires-Dist: Jinja2
Requires-Dist: ruamel.yaml
Requires-Dist: pyodbc
Requires-Dist: openai
Requires-Dist: pydantic
Requires-Dist: alive_progress
Dynamic: author
Dynamic: author-email
Dynamic: classifier
Dynamic: description
Dynamic: description-content-type
Dynamic: home-page
Dynamic: requires-dist
Dynamic: requires-python
Dynamic: summary
